django_restful_response
